Metadata-Version: 2.1
Name: tts-eval
Version: 0.0.1
Summary: TTS Evaluation
Home-page: https://github.com/kotoba-tech/tts_eval
Author: Asahi Ushio
Author-email: asahi1992ushio@gmail.com
License: MIT
Keywords: machine-learning
Platform: UNKNOWN
Classifier: Development Status :: 4 - Beta
Classifier: Intended Audience :: Developers
Classifier: Intended Audience :: Science/Research
Classifier: Topic :: Scientific/Engineering
Classifier: License :: OSI Approved :: MIT License
Classifier: Programming Language :: Python :: 3
Requires-Python: >=3.8
